<annotation>
	<folder>new</folder>
	<filename>168.jpg</filename>
	<path>C:\Users\92cha\Desktop\new\168.jpg</path>
	<source>
		<database>Unknown</database>
	</source>
	<size>
		<width>300</width>
		<height>300</height>
		<depth>3</depth>
	</size>
	<segmented>0</segmented>
	<object>
		<name>po</name>
		<pose>Unspecified</pose>
		<truncated>0</truncated>
		<difficult>0</difficult>
		<bndbox>
			<xmin>159</xmin>
			<ymin>98</ymin>
			<xmax>245</xmax>
			<ymax>261</ymax>
		</bndbox>
	</object>
	<object>
		<name>shifu</name>
		<pose>Unspecified</pose>
		<truncated>1</truncated>
		<difficult>0</difficult>
		<bndbox>
			<xmin>1</xmin>
			<ymin>50</ymin>
			<xmax>130</xmax>
			<ymax>261</ymax>
		</bndbox>
	</object>
</annotation>
